spacer_tutorial/__init__.py
spacer_tutorial/bakery.py
spacer_tutorial/cfa.py
spacer_tutorial/chc.py
spacer_tutorial/dcfa.py
spacer_tutorial/fml.py
spacer_tutorial/proof.py
spacer_tutorial/solve.py
spacer_tutorial/ts.py
spacer_tutorial/vcgen.py
spacer_tutorial/xnet.py
spacer_tutorial-0.0.3.dist-info/METADATA
spacer_tutorial-0.0.3.dist-info/WHEEL
spacer_tutorial-0.0.3.dist-info/licenses/LICENSE
spacer_tutorial-0.0.3.dist-info/RECORD
