Metadata-Version: 2.1
Name: spacer_tutorial
Version: 0.0.3
Summary: Transition systems and other support for Spacer Jupyter Tutorial
Project-URL: Homepage, https://github.com/agurfinkel/spacer-on-jupyter
Project-URL: Bug Tracker, https://github.com/agurfinkel/spacer-on-jupyter/issues
Author-email: Arie Gurfinkel <arie.gurfinkel@uwaterloo.ca>
License-File: LICENSE
Classifier: License :: OSI Approved :: MIT License
Classifier: Operating System :: OS Independent
Classifier: Programming Language :: Python :: 3
Requires-Python: >=3.9
